molingtools/__init__.py
molingtools/calendar.py
molingtools/notice.py
molingtools/pdf_tool.py
molingtools/time.py
molingtools/video_tool.py
molingtools/__pycache__/__init__.cpython-312.pyc
molingtools/asynct/mcp.py
molingtools/asynct/websocket.py
molingtools/asynct/mcp_old/again_client_session.py
molingtools/asynct/mcp_old/client.py
molingtools/asynct/task/__init__.py
molingtools/asynct/task/asynct.py
molingtools/asynct/task/model.py
molingtools/asynct/task/process.py
molingtools/asynct/task/thread.py
molingtools/deep_learning/network_tool.py
molingtools/deep_learning/tool.py
molingtools/flow/mg_task_dispatch.py
molingtools/flow/thread_work.py
molingtools/nosql/milvus.py
molingtools/nosql/mongo.py
molingtools/sqltool/mysql.py
molingtools/sqltool/pgsql.py
molingtools/sqltool/sqlite.py
molingtools/sqltool/sqlserver.py
molingtools/sqltool/tools.py
molingtools/sqltool/__sqltool__/action.py
molingtools/sqltool/__sqltool__/alter.py
molingtools/sqltool/__sqltool__/body.py
molingtools/template/__init__.py
molingtools/template/__pycache__/__init__.cpython-312.pyc
molingtools/template/project/.gitignore_exp
molingtools/template/project/README.md_exp
molingtools/template/project/config.py
molingtools/template/project/config_private.yaml
molingtools/template/project/config_private.yaml.example
molingtools/template/project/pyproject.toml
molingtools/template/project/run.sh
molingtools/template/project/public/__init__.py
molingtools/template/project/public/model.py
molingtools-1.1.13.dist-info/METADATA
molingtools-1.1.13.dist-info/WHEEL
molingtools-1.1.13.dist-info/entry_points.txt
molingtools-1.1.13.dist-info/top_level.txt
molingtools-1.1.13.dist-info/RECORD
