Metadata-Version: 2.4
Name: molingtools
Version: 1.1.13
Summary: 多功能工具包
Home-page: https://www.python.org
Author: mengling
Author-email: 1321443305@qq.com
Requires-Python: >=3.8
Requires-Dist: click
Requires-Dist: tqdm
Requires-Dist: pydantic
Provides-Extra: mcp
Requires-Dist: mcp; extra == "mcp"
Requires-Dist: openai; extra == "mcp"
Provides-Extra: sql
Requires-Dist: pymysql; extra == "sql"
Requires-Dist: psycopg2-binary; extra == "sql"
Requires-Dist: pyDes; extra == "sql"
Dynamic: author
Dynamic: author-email
Dynamic: home-page
Dynamic: provides-extra
Dynamic: requires-dist
Dynamic: requires-python
Dynamic: summary
